calciiii/__init__.py
calciiii/add.py
calciiii/subtract.py
calciiii-0.0.1.dist-info/METADATA
calciiii-0.0.1.dist-info/WHEEL
calciiii-0.0.1.dist-info/top_level.txt
calciiii-0.0.1.dist-info/RECORD
